pytest_remove_stale_bytecode.py
pytest_remove_stale_bytecode-7.0.dist-info/licenses/LICENSE.txt
pytest_remove_stale_bytecode-7.0.dist-info/METADATA
pytest_remove_stale_bytecode-7.0.dist-info/WHEEL
pytest_remove_stale_bytecode-7.0.dist-info/entry_points.txt
pytest_remove_stale_bytecode-7.0.dist-info/top_level.txt
pytest_remove_stale_bytecode-7.0.dist-info/RECORD
